<?xml version="1.0" encoding="iso-8859-1"?>
<estoque>
<APIQueBarato>46d98f74be65a44e8848d48e4d8dc48e</APIQueBarato>
<UsuarioQueBarato>Y29udGF0b0BxdWVyb2NhcnJvcy5jb20=</UsuarioQueBarato>
<SenhaQueBarato>cm8yMzQyMzE=</SenhaQueBarato>
<concessionaria>
<razaosocial>Cristiano Souza da Silva ME.</razaosocial>
<nomefantasia>SouzaVeículos</nomefantasia>
<cnpj>01968052000119</cnpj>
<logradouro>Rua das magnólias</logradouro>
<numero>356</numero>
<bairro>Jd. Florida</bairro>
<cidade>Embu</cidade>
<uf>SP</uf>
<cep>06810-110</cep>
<telefone>(11)4783-4722</telefone>
<email>comercial@souzaveiculos.com.br</email>
<veiculo>
<idQueBarato>11314837</idQueBarato>
<cnpj_con>01968052000119</cnpj_con>
<idveiculo>1103</idveiculo>
<tipoveiculo>Carro</tipoveiculo>
<zerokm>N</zerokm>
<placa>EKZ2085</placa>
<titulo>HYUNDAI TUCSON 2009 2.0 GASOLINA</titulo>
<marca>Hyundai</marca>
<modelo>Tucson</modelo>
<versao><![CDATA[Tucson 2.0 16V Aut.]]></versao>
<ano_fabricacao>2009</ano_fabricacao>
<ano_modelo>2010</ano_modelo>
<portas>4</portas>
<motorizacao>2.0</motorizacao>
<combustivel>Gasolina</combustivel>
<cor>Preto</cor>
<cambio>Manual</cambio>
<final_placa>5</final_placa>
<quilometragem>60000</quilometragem>
<descricao><![CDATA[Veículo HYUNDAI 206 SELECTION 2.0 2009/2010 GASOLINA de cor Preto com ótimo preço. Viabilizamos financiamento em ate 60 Meses, fazemos Troca com Troco. Temos parceria com diversos bancos e financeiras. Aceitamos seu usado na troca. Veículos revisados e com garantia.<br><br>Revenda: Souza Veículos - Para entrar em contato com esta revenda ligue para (11)4783-4722 e informe o CÓDIGO DO ANÚNCIO: 00001103.<br><br>Veja mais anúncios desta revenda em <a href='http://www.querocarros.com'>www.querocarros.com</a><br><br>Anúncio publicado através do it-Car. ]]></descricao>
<preco>47900</preco>
<observacoes></observacoes>
<tipo>Usado</tipo>
<procedencia>Importado</procedencia>
<opcionais>
<opcional>Volante com regulagem de altura</opcional>
<opcional>Vidros elétricos dianteiros e traseiros</opcional>
<opcional>Travas elétricas</opcional>
<opcional>Trava central</opcional>
<opcional>Rodas de Liga Leve</opcional>
<opcional>Retrovisores Elétricos</opcional>
<opcional>Retrovisor na cor do veículo</opcional>
<opcional>Protetor para motor e cárter</opcional>
<opcional>Porta-copos</opcional>
<opcional>Piloto automático</opcional>
<opcional>Para-Choque na cor do veículo</opcional>
<opcional>Maçaneta na cor do veículo</opcional>
<opcional>Limpador traseiro</opcional>
<opcional>Insul Film</opcional>
<opcional>Farol de Xenônio</opcional>
<opcional>Farol de neblina</opcional>
<opcional>Espelhos elétricos</opcional>
<opcional>Entrada USB</opcional>
<opcional>Encosto de cabeça traseiro</opcional>
<opcional>Direção hidráulica</opcional>
<opcional>Desembaçador traseiro</opcional>
<opcional>Computador de bordo</opcional>
<opcional>CD player</opcional>
<opcional>Câmbio automático</opcional>
<opcional>Ar-quente</opcional>
<opcional>Ar-condicionado</opcional>
<opcional>Alarme à distância</opcional>
<opcional>Alarme</opcional>
<opcional>Airbag passageiro</opcional>
<opcional>Airbag motorista</opcional>
</opcionais>
<fotos>
<foto>http://www.souzaveiculos.com.br/veiculos/001103/GRANDE_001103_1.jpg</foto>
<foto>http://www.souzaveiculos.com.br/veiculos/001103/GRANDE_001103_2.jpg</foto>
<foto>http://www.souzaveiculos.com.br/veiculos/001103/GRANDE_001103_3.jpg</foto>
</fotos>
<data>11/11/2013</data>
</veiculo>
<veiculo>
<idQueBarato>11314839</idQueBarato>
<cnpj_con></cnpj_con>
<idveiculo>1103</idveiculo>
<tipoveiculo>Carro</tipoveiculo>
<zerokm>N</zerokm>
<placa>EKZ2085</placa>
<titulo>HYUNDAI TUCSON 2009 2.0 GASOLINA</titulo>
<marca>Hyundai</marca>
<modelo>Tucson</modelo>
<versao><![CDATA[Tucson 2.0 16V Aut.]]></versao>
<ano_fabricacao>2009</ano_fabricacao>
<ano_modelo>2010</ano_modelo>
<portas>4</portas>
<motorizacao>2.0</motorizacao>
<combustivel>Gasolina</combustivel>
<cor>Preto</cor>
<cambio>Manual</cambio>
<final_placa>5</final_placa>
<quilometragem>60000</quilometragem>
<descricao><![CDATA[Veículo HYUNDAI TUCSON 2.0 2009/2010 GASOLINA de cor Preto com ótimo preço. Viabilizamos financiamento em ate 60 Meses, fazemos Troca com Troco. Temos parceria com diversos bancos e financeiras. Aceitamos seu usado na troca. Veículos revisados e com garantia.<br><br>Revenda: Souza Veículos - Para entrar em contato com esta revenda ligue para (11)4203-2689 e informe o CÓDIGO DO ANÚNCIO: 00001103.<br><br>Veja mais anúncios desta revenda em <a href='http://www.querocarros.com'>www.querocarros.com</a><br><br>Anúncio publicado através do it-Car. ]]></descricao>
<preco>47900</preco>
<observacoes></observacoes>
<tipo>Usado</tipo>
<procedencia>Importado</procedencia>
<opcionais>
<opcional>Volante com regulagem de altura</opcional>
<opcional>Vidros elétricos dianteiros e traseiros</opcional>
<opcional>Travas elétricas</opcional>
<opcional>Trava central</opcional>
<opcional>Rodas de Liga Leve</opcional>
<opcional>Retrovisores Elétricos</opcional>
<opcional>Retrovisor na cor do veículo</opcional>
<opcional>Protetor para motor e cárter</opcional>
<opcional>Porta-copos</opcional>
<opcional>Piloto automático</opcional>
<opcional>Para-Choque na cor do veículo</opcional>
<opcional>Maçaneta na cor do veículo</opcional>
<opcional>Limpador traseiro</opcional>
<opcional>Insul Film</opcional>
<opcional>Farol de Xenônio</opcional>
<opcional>Farol de neblina</opcional>
<opcional>Espelhos elétricos</opcional>
<opcional>Entrada USB</opcional>
<opcional>Encosto de cabeça traseiro</opcional>
<opcional>Direção hidráulica</opcional>
<opcional>Desembaçador traseiro</opcional>
<opcional>Computador de bordo</opcional>
<opcional>CD player</opcional>
<opcional>Câmbio automático</opcional>
<opcional>Ar-quente</opcional>
<opcional>Ar-condicionado</opcional>
<opcional>Alarme à distância</opcional>
<opcional>Alarme</opcional>
<opcional>Airbag passageiro</opcional>
<opcional>Airbag motorista</opcional>
</opcionais>
<fotos>
<foto>http://www.souzaveiculos.com.br/veiculos/001103/GRANDE_001103_1.jpg</foto>
<foto>http://www.souzaveiculos.com.br/veiculos/001103/GRANDE_001103_2.jpg</foto>
<foto>http://www.souzaveiculos.com.br/veiculos/001103/GRANDE_001103_3.jpg</foto>
</fotos>
<data>11/11/2013</data>
</veiculo>
<veiculo>
<idQueBarato>11314841</idQueBarato>
<cnpj_con>01968052000119</cnpj_con>
<idveiculo>1136</idveiculo>
<tipoveiculo>Carro</tipoveiculo>
<zerokm>N</zerokm>
<placa>EBM8846</placa>
<titulo>VOLKSWAGEN JETTA 2007 2.5 GASOLINA</titulo>
<marca>Volkswagen</marca>
<modelo>Jetta</modelo>
<versao><![CDATA[JETTA 2.5 20V 150/170cv Tiptronic]]></versao>
<ano_fabricacao>2007</ano_fabricacao>
<ano_modelo>2008</ano_modelo>
<portas>4</portas>
<motorizacao>2.5</motorizacao>
<combustivel>Gasolina</combustivel>
<cor>Prata</cor>
<cambio>Automática</cambio>
<final_placa>6</final_placa>
<quilometragem>80119</quilometragem>
<descricao><![CDATA[Veículo VOLKSWAGEN TUCSON 2.5 2007/2008 GASOLINA de cor Prata com ótimo preço. Viabilizamos financiamento em ate 60 Meses, fazemos Troca com Troco. Temos parceria com diversos bancos e financeiras. Aceitamos seu usado na troca. Veículos revisados e com garantia.<br><br>Revenda: Souza Veículos - Para entrar em contato com esta revenda ligue para (11)4783-4722 e informe o CÓDIGO DO ANÚNCIO: 00001136.<br><br>Veja mais anúncios desta revenda em <a href='http://www.querocarros.com'>www.querocarros.com</a><br><br>Anúncio publicado através do it-Car. ]]></descricao>
<preco>41900</preco>
<observacoes></observacoes>
<tipo>Usado</tipo>
<procedencia>Importado</procedencia>
<opcionais>
<opcional>Vidros elétricos dianteiros e traseiros</opcional>
<opcional>Travas elétricas</opcional>
<opcional>Trava central</opcional>
<opcional>Retrovisores Elétricos</opcional>
<opcional>Rádio FM/AM</opcional>
<opcional>Limpador traseiro</opcional>
<opcional>Insul Film</opcional>
<opcional>DVD Player</opcional>
<opcional>Direção hidráulica</opcional>
<opcional>Desembaçador traseiro</opcional>
<opcional>Computador de bordo</opcional>
<opcional>CD player</opcional>
<opcional>Câmbio automático</opcional>
<opcional>Bancos de couro</opcional>
<opcional>Ar-condicionado</opcional>
<opcional>Alarme à distância</opcional>
<opcional>Alarme</opcional>
<opcional>Airbag motorista</opcional>
</opcionais>
<fotos>
<foto>http://www.souzaveiculos.com.br/veiculos/001136/GRANDE_001136_1.jpg</foto>
<foto>http://www.souzaveiculos.com.br/veiculos/001136/GRANDE_001136_2.jpg</foto>
<foto>http://www.souzaveiculos.com.br/veiculos/001136/GRANDE_001136_3.jpg</foto>
</fotos>
<data>11/11/2013</data>
</veiculo>
<veiculo>
<idQueBarato>11314842</idQueBarato>
<cnpj_con></cnpj_con>
<idveiculo>1136</idveiculo>
<tipoveiculo>Carro</tipoveiculo>
<zerokm>N</zerokm>
<placa>EBM8846</placa>
<titulo>VOLKSWAGEN JETTA 2007 2.5 GASOLINA</titulo>
<marca>Volkswagen</marca>
<modelo>Jetta</modelo>
<versao><![CDATA[JETTA 2.5 20V 150/170cv Tiptronic]]></versao>
<ano_fabricacao>2007</ano_fabricacao>
<ano_modelo>2008</ano_modelo>
<portas>4</portas>
<motorizacao>2.5</motorizacao>
<combustivel>Gasolina</combustivel>
<cor>Prata</cor>
<cambio>Automática</cambio>
<final_placa>6</final_placa>
<quilometragem>80119</quilometragem>
<descricao><![CDATA[Veículo VOLKSWAGEN JETTA 2.5 2007/2008 GASOLINA de cor Prata com ótimo preço. Viabilizamos financiamento em ate 60 Meses, fazemos Troca com Troco. Temos parceria com diversos bancos e financeiras. Aceitamos seu usado na troca. Veículos revisados e com garantia.<br><br>Revenda: Souza Veículos - Para entrar em contato com esta revenda ligue para (11)4203-2689 e informe o CÓDIGO DO ANÚNCIO: 00001136.<br><br>Veja mais anúncios desta revenda em <a href='http://www.querocarros.com'>www.querocarros.com</a><br><br>Anúncio publicado através do it-Car. ]]></descricao>
<preco>41900</preco>
<observacoes></observacoes>
<tipo>Usado</tipo>
<procedencia>Importado</procedencia>
<opcionais>
<opcional>Vidros elétricos dianteiros e traseiros</opcional>
<opcional>Travas elétricas</opcional>
<opcional>Trava central</opcional>
<opcional>Retrovisores Elétricos</opcional>
<opcional>Rádio FM/AM</opcional>
<opcional>Limpador traseiro</opcional>
<opcional>Insul Film</opcional>
<opcional>DVD Player</opcional>
<opcional>Direção hidráulica</opcional>
<opcional>Desembaçador traseiro</opcional>
<opcional>Computador de bordo</opcional>
<opcional>CD player</opcional>
<opcional>Câmbio automático</opcional>
<opcional>Bancos de couro</opcional>
<opcional>Ar-condicionado</opcional>
<opcional>Alarme à distância</opcional>
<opcional>Alarme</opcional>
<opcional>Airbag motorista</opcional>
</opcionais>
<fotos>
<foto>http://www.souzaveiculos.com.br/veiculos/001136/GRANDE_001136_1.jpg</foto>
<foto>http://www.souzaveiculos.com.br/veiculos/001136/GRANDE_001136_2.jpg</foto>
<foto>http://www.souzaveiculos.com.br/veiculos/001136/GRANDE_001136_3.jpg</foto>
</fotos>
<data>11/11/2013</data>
</veiculo>
<veiculo>
<idQueBarato>11314843</idQueBarato>
<cnpj_con>01968052000119</cnpj_con>
<idveiculo>1141</idveiculo>
<tipoveiculo>Carro</tipoveiculo>
<zerokm>S</zerokm>
<placa>AAA1230</placa>
<titulo>FORD ECOSPORT 2013 1.6 FLEX</titulo>
<marca>Ford</marca>
<modelo>Ecosport</modelo>
<versao><![CDATA[EcoSport FREESTYLE 1.6 16V Flex 5p]]></versao>
<ano_fabricacao>2013</ano_fabricacao>
<ano_modelo>2013</ano_modelo>
<portas>4</portas>
<motorizacao>1.6</motorizacao>
<combustivel>Flex</combustivel>
<cor>Preto</cor>
<cambio>Manual</cambio>
<final_placa>0</final_placa>
<quilometragem>0</quilometragem>
<descricao><![CDATA[Veículo FORD JETTA 1.6 2013/2013 FLEX de cor Preto com ótimo preço. Viabilizamos financiamento em ate 60 Meses, fazemos Troca com Troco. Temos parceria com diversos bancos e financeiras. Aceitamos seu usado na troca. Veículos revisados e com garantia.<br><br>Revenda: Souza Veículos - Para entrar em contato com esta revenda ligue para (11)4783-4722 e informe o CÓDIGO DO ANÚNCIO: 00001141.<br><br>Veja mais anúncios desta revenda em <a href='http://www.querocarros.com'>www.querocarros.com</a><br><br>Anúncio publicado através do it-Car. ]]></descricao>
<preco>58900</preco>
<observacoes></observacoes>
<tipo>Novo</tipo>
<procedencia>Nacional</procedencia>
<opcionais>
<opcional>Vidros elétricos dianteiros e traseiros</opcional>
<opcional>Vidros elétricos dianteiros</opcional>
<opcional>Travas elétricas</opcional>
<opcional>Trava central</opcional>
<opcional>Sensor de estacionamento</opcional>
<opcional>Sensor crepuscular</opcional>
<opcional>Retrovisores Elétricos</opcional>
<opcional>Retrovisor na cor do veículo</opcional>
<opcional>Rádio FM/AM</opcional>
<opcional>Protetor para motor e cárter</opcional>
<opcional>Para-Choque na cor do veículo</opcional>
<opcional>Maçaneta na cor do veículo</opcional>
<opcional>Limpador traseiro</opcional>
<opcional>Espelhos elétricos</opcional>
<opcional>Entrada USB</opcional>
<opcional>Encosto de cabeça traseiro</opcional>
<opcional>Direção hidráulica</opcional>
<opcional>Desembaçador traseiro</opcional>
<opcional>Computador de bordo</opcional>
<opcional>CD player com MP3</opcional>
<opcional>CD player</opcional>
<opcional>Câmbio manual</opcional>
<opcional>Banco motorista com ajuste de altura</opcional>
<opcional>Ar-quente</opcional>
<opcional>Ar-condicionado</opcional>
<opcional>Alarme à distância</opcional>
<opcional>Alarme</opcional>
<opcional>Airbag passageiro</opcional>
<opcional>Airbag motorista</opcional>
</opcionais>
<fotos>
<foto>http://www.souzaveiculos.com.br/veiculos/001141/GRANDE_001141_1.jpg</foto>
<foto>http://www.souzaveiculos.com.br/veiculos/001141/GRANDE_001141_2.jpg</foto>
<foto>http://www.souzaveiculos.com.br/veiculos/001141/GRANDE_001141_3.jpg</foto>
<foto>http://www.souzaveiculos.com.br/veiculos/001141/GRANDE_001141_4.jpg</foto>
<foto>http://www.souzaveiculos.com.br/veiculos/001141/GRANDE_001141_5.jpg</foto>
<foto>http://www.souzaveiculos.com.br/veiculos/001141/GRANDE_001141_6.jpg</foto>
</fotos>
<data>11/11/2013</data>
</veiculo>
<veiculo>
<idQueBarato>11314846</idQueBarato>
<cnpj_con></cnpj_con>
<idveiculo>1141</idveiculo>
<tipoveiculo>Carro</tipoveiculo>
<zerokm>S</zerokm>
<placa>AAA1230</placa>
<titulo>FORD ECOSPORT 2013 1.6 FLEX</titulo>
<marca>Ford</marca>
<modelo>Ecosport</modelo>
<versao><![CDATA[EcoSport FREESTYLE 1.6 16V Flex 5p]]></versao>
<ano_fabricacao>2013</ano_fabricacao>
<ano_modelo>2013</ano_modelo>
<portas>4</portas>
<motorizacao>1.6</motorizacao>
<combustivel>Flex</combustivel>
<cor>Preto</cor>
<cambio>Manual</cambio>
<final_placa>0</final_placa>
<quilometragem>0</quilometragem>
<descricao><![CDATA[Veículo FORD ECOSPORT 1.6 2013/2013 FLEX de cor Preto com ótimo preço. Viabilizamos financiamento em ate 60 Meses, fazemos Troca com Troco. Temos parceria com diversos bancos e financeiras. Aceitamos seu usado na troca. Veículos revisados e com garantia.<br><br>Revenda: Souza Veículos - Para entrar em contato com esta revenda ligue para (11)4203-2689 e informe o CÓDIGO DO ANÚNCIO: 00001141.<br><br>Veja mais anúncios desta revenda em <a href='http://www.querocarros.com'>www.querocarros.com</a><br><br>Anúncio publicado através do it-Car. ]]></descricao>
<preco>58900</preco>
<observacoes></observacoes>
<tipo>Novo</tipo>
<procedencia>Nacional</procedencia>
<opcionais>
<opcional>Vidros elétricos dianteiros e traseiros</opcional>
<opcional>Vidros elétricos dianteiros</opcional>
<opcional>Travas elétricas</opcional>
<opcional>Trava central</opcional>
<opcional>Sensor de estacionamento</opcional>
<opcional>Sensor crepuscular</opcional>
<opcional>Retrovisores Elétricos</opcional>
<opcional>Retrovisor na cor do veículo</opcional>
<opcional>Rádio FM/AM</opcional>
<opcional>Protetor para motor e cárter</opcional>
<opcional>Para-Choque na cor do veículo</opcional>
<opcional>Maçaneta na cor do veículo</opcional>
<opcional>Limpador traseiro</opcional>
<opcional>Espelhos elétricos</opcional>
<opcional>Entrada USB</opcional>
<opcional>Encosto de cabeça traseiro</opcional>
<opcional>Direção hidráulica</opcional>
<opcional>Desembaçador traseiro</opcional>
<opcional>Computador de bordo</opcional>
<opcional>CD player com MP3</opcional>
<opcional>CD player</opcional>
<opcional>Câmbio manual</opcional>
<opcional>Banco motorista com ajuste de altura</opcional>
<opcional>Ar-quente</opcional>
<opcional>Ar-condicionado</opcional>
<opcional>Alarme à distância</opcional>
<opcional>Alarme</opcional>
<opcional>Airbag passageiro</opcional>
<opcional>Airbag motorista</opcional>
</opcionais>
<fotos>
<foto>http://www.souzaveiculos.com.br/veiculos/001141/GRANDE_001141_1.jpg</foto>
<foto>http://www.souzaveiculos.com.br/veiculos/001141/GRANDE_001141_2.jpg</foto>
<foto>http://www.souzaveiculos.com.br/veiculos/001141/GRANDE_001141_3.jpg</foto>
<foto>http://www.souzaveiculos.com.br/veiculos/001141/GRANDE_001141_4.jpg</foto>
<foto>http://www.souzaveiculos.com.br/veiculos/001141/GRANDE_001141_5.jpg</foto>
<foto>http://www.souzaveiculos.com.br/veiculos/001141/GRANDE_001141_6.jpg</foto>
</fotos>
<data>11/11/2013</data>
</veiculo>
<veiculo>
<idQueBarato>11314750</idQueBarato>
<cnpj_con>01968052000119</cnpj_con>
<idveiculo>1185</idveiculo>
<tipoveiculo>Moto</tipoveiculo>
<zerokm>N</zerokm>
<placa>EXL</placa>
<titulo>HONDA CG 125 2012 125 GASOLINA</titulo>
<marca>Honda</marca>
<modelo>Cg 125</modelo>
<versao><![CDATA[]]></versao>
<ano_fabricacao>2012</ano_fabricacao>
<ano_modelo>2012</ano_modelo>
<portas>2</portas>
<motorizacao>125</motorizacao>
<combustivel>Gasolina</combustivel>
<cor>Vermelho</cor>
<cambio>Manual</cambio>
<final_placa>L</final_placa>
<quilometragem>95623</quilometragem>
<descricao><![CDATA[Veículo HONDA ECOSPORT 125 2012/2012 GASOLINA de cor Vermelho com ótimo preço. Viabilizamos financiamento em ate 60 Meses, fazemos Troca com Troco. Temos parceria com diversos bancos e financeiras. Aceitamos seu usado na troca. Veículos revisados e com garantia.<br><br>Revenda: Souza Veículos - Para entrar em contato com esta revenda ligue para (11)4783-4722 e informe o CÓDIGO DO ANÚNCIO: 00001185.<br><br>Veja mais anúncios desta revenda em <a href='http://www.querocarros.com'>www.querocarros.com</a><br><br>Anúncio publicado através do it-Car. ]]></descricao>
<preco>4900</preco>
<observacoes></observacoes>
<tipo>Usado</tipo>
<procedencia>Nacional</procedencia>
<opcionais>
</opcionais>
<fotos>
<foto>http://www.souzaveiculos.com.br/veiculos/001185/GRANDE_001185_1.jpg</foto>
<foto>http://www.souzaveiculos.com.br/veiculos/001185/GRANDE_001185_2.jpg</foto>
<foto>http://www.souzaveiculos.com.br/veiculos/001185/GRANDE_001185_3.jpg</foto>
<foto>http://www.souzaveiculos.com.br/veiculos/001185/GRANDE_001185_4.jpg</foto>
<foto>http://www.souzaveiculos.com.br/veiculos/001185/GRANDE_001185_5.jpg</foto>
<foto>http://www.souzaveiculos.com.br/veiculos/001185/GRANDE_001185_6.jpg</foto>
</fotos>
<data>11/11/2013</data>
</veiculo>
<veiculo>
<idQueBarato>11314850</idQueBarato>
<cnpj_con></cnpj_con>
<idveiculo>1185</idveiculo>
<tipoveiculo>Moto</tipoveiculo>
<zerokm>N</zerokm>
<placa>EXL</placa>
<titulo>HONDA CG 125 2012 125 GASOLINA</titulo>
<marca>Honda</marca>
<modelo>Cg 125</modelo>
<versao><![CDATA[]]></versao>
<ano_fabricacao>2012</ano_fabricacao>
<ano_modelo>2012</ano_modelo>
<portas>2</portas>
<motorizacao>125</motorizacao>
<combustivel>Gasolina</combustivel>
<cor>Vermelho</cor>
<cambio>Manual</cambio>
<final_placa>L</final_placa>
<quilometragem>95623</quilometragem>
<descricao><![CDATA[Veículo HONDA CG 125 125 2012/2012 GASOLINA de cor Vermelho com ótimo preço. Viabilizamos financiamento em ate 60 Meses, fazemos Troca com Troco. Temos parceria com diversos bancos e financeiras. Aceitamos seu usado na troca. Veículos revisados e com garantia.<br><br>Revenda: Souza Veículos - Para entrar em contato com esta revenda ligue para (11)4203-2689 e informe o CÓDIGO DO ANÚNCIO: 00001185.<br><br>Veja mais anúncios desta revenda em <a href='http://www.querocarros.com'>www.querocarros.com</a><br><br>Anúncio publicado através do it-Car. ]]></descricao>
<preco>4900</preco>
<observacoes></observacoes>
<tipo>Usado</tipo>
<procedencia>Nacional</procedencia>
<opcionais>
</opcionais>
<fotos>
<foto>http://www.souzaveiculos.com.br/veiculos/001185/GRANDE_001185_1.jpg</foto>
<foto>http://www.souzaveiculos.com.br/veiculos/001185/GRANDE_001185_2.jpg</foto>
<foto>http://www.souzaveiculos.com.br/veiculos/001185/GRANDE_001185_3.jpg</foto>
<foto>http://www.souzaveiculos.com.br/veiculos/001185/GRANDE_001185_4.jpg</foto>
<foto>http://www.souzaveiculos.com.br/veiculos/001185/GRANDE_001185_5.jpg</foto>
<foto>http://www.souzaveiculos.com.br/veiculos/001185/GRANDE_001185_6.jpg</foto>
</fotos>
<data>11/11/2013</data>
</veiculo>
<veiculo>
<idQueBarato>11314854</idQueBarato>
<cnpj_con>01968052000119</cnpj_con>
<idveiculo>1152</idveiculo>
<tipoveiculo>Carro</tipoveiculo>
<zerokm>S</zerokm>
<placa>XXX1230</placa>
<titulo>VOLKSWAGEN FOX 2013 1.6 FLEX</titulo>
<marca>Volkswagen</marca>
<modelo>Fox</modelo>
<versao><![CDATA[]]></versao>
<ano_fabricacao>2013</ano_fabricacao>
<ano_modelo>2013</ano_modelo>
<portas>4</portas>
<motorizacao>1.6</motorizacao>
<combustivel>Flex</combustivel>
<cor>Vermelho</cor>
<cambio>Manual</cambio>
<final_placa>0</final_placa>
<quilometragem>0</quilometragem>
<descricao><![CDATA[Veículo VOLKSWAGEN CG 125 1.6 2013/2013 FLEX de cor Vermelho com ótimo preço. Viabilizamos financiamento em ate 60 Meses, fazemos Troca com Troco. Temos parceria com diversos bancos e financeiras. Aceitamos seu usado na troca. Veículos revisados e com garantia.<br><br>Revenda: Souza Veículos - Para entrar em contato com esta revenda ligue para (11)4783-4722 e informe o CÓDIGO DO ANÚNCIO: 00001152.<br><br>Veja mais anúncios desta revenda em <a href='http://www.querocarros.com'>www.querocarros.com</a><br><br>Anúncio publicado através do it-Car. ]]></descricao>
<preco>37900</preco>
<observacoes></observacoes>
<tipo>Novo</tipo>
<procedencia>Nacional</procedencia>
<opcionais>
<opcional>Vidros elétricos dianteiros e traseiros</opcional>
<opcional>Travas elétricas</opcional>
<opcional>Trava central</opcional>
<opcional>Retrovisores Elétricos</opcional>
<opcional>Retrovisor na cor do veículo</opcional>
<opcional>Rádio FM/AM</opcional>
<opcional>Porta-copos</opcional>
<opcional>Para-Choque na cor do veículo</opcional>
<opcional>Maçaneta na cor do veículo</opcional>
<opcional>Limpador traseiro</opcional>
<opcional>Freios ABS</opcional>
<opcional>Espelhos elétricos</opcional>
<opcional>Entrada USB</opcional>
<opcional>Encosto de cabeça traseiro</opcional>
<opcional>Direção hidráulica</opcional>
<opcional>Desembaçador traseiro</opcional>
<opcional>Chave codificada (Code)</opcional>
<opcional>CD player com MP3</opcional>
<opcional>CD player</opcional>
<opcional>Câmbio manual</opcional>
<opcional>Ar-quente</opcional>
<opcional>Ar-condicionado</opcional>
<opcional>Alarme</opcional>
<opcional>Airbag passageiro</opcional>
<opcional>Airbag motorista</opcional>
</opcionais>
<fotos>
<foto>http://www.souzaveiculos.com.br/veiculos/001152/GRANDE_001152_1.jpg</foto>
<foto>http://www.souzaveiculos.com.br/veiculos/001152/GRANDE_001152_2.jpg</foto>
<foto>http://www.souzaveiculos.com.br/veiculos/001152/GRANDE_001152_3.jpg</foto>
<foto>http://www.souzaveiculos.com.br/veiculos/001152/GRANDE_001152_4.jpg</foto>
</fotos>
<data>11/11/2013</data>
</veiculo>
<veiculo>
<idQueBarato>11314855</idQueBarato>
<cnpj_con></cnpj_con>
<idveiculo>1152</idveiculo>
<tipoveiculo>Carro</tipoveiculo>
<zerokm>S</zerokm>
<placa>XXX1230</placa>
<titulo>VOLKSWAGEN FOX 2013 1.6 FLEX</titulo>
<marca>Volkswagen</marca>
<modelo>Fox</modelo>
<versao><![CDATA[]]></versao>
<ano_fabricacao>2013</ano_fabricacao>
<ano_modelo>2013</ano_modelo>
<portas>4</portas>
<motorizacao>1.6</motorizacao>
<combustivel>Flex</combustivel>
<cor>Vermelho</cor>
<cambio>Manual</cambio>
<final_placa>0</final_placa>
<quilometragem>0</quilometragem>
<descricao><![CDATA[Veículo VOLKSWAGEN FOX 1.6 2013/2013 FLEX de cor Vermelho com ótimo preço. Viabilizamos financiamento em ate 60 Meses, fazemos Troca com Troco. Temos parceria com diversos bancos e financeiras. Aceitamos seu usado na troca. Veículos revisados e com garantia.<br><br>Revenda: Souza Veículos - Para entrar em contato com esta revenda ligue para (11)4203-2689 e informe o CÓDIGO DO ANÚNCIO: 00001152.<br><br>Veja mais anúncios desta revenda em <a href='http://www.querocarros.com'>www.querocarros.com</a><br><br>Anúncio publicado através do it-Car. ]]></descricao>
<preco>37900</preco>
<observacoes></observacoes>
<tipo>Novo</tipo>
<procedencia>Nacional</procedencia>
<opcionais>
<opcional>Vidros elétricos dianteiros e traseiros</opcional>
<opcional>Travas elétricas</opcional>
<opcional>Trava central</opcional>
<opcional>Retrovisores Elétricos</opcional>
<opcional>Retrovisor na cor do veículo</opcional>
<opcional>Rádio FM/AM</opcional>
<opcional>Porta-copos</opcional>
<opcional>Para-Choque na cor do veículo</opcional>
<opcional>Maçaneta na cor do veículo</opcional>
<opcional>Limpador traseiro</opcional>
<opcional>Freios ABS</opcional>
<opcional>Espelhos elétricos</opcional>
<opcional>Entrada USB</opcional>
<opcional>Encosto de cabeça traseiro</opcional>
<opcional>Direção hidráulica</opcional>
<opcional>Desembaçador traseiro</opcional>
<opcional>Chave codificada (Code)</opcional>
<opcional>CD player com MP3</opcional>
<opcional>CD player</opcional>
<opcional>Câmbio manual</opcional>
<opcional>Ar-quente</opcional>
<opcional>Ar-condicionado</opcional>
<opcional>Alarme</opcional>
<opcional>Airbag passageiro</opcional>
<opcional>Airbag motorista</opcional>
</opcionais>
<fotos>
<foto>http://www.souzaveiculos.com.br/veiculos/001152/GRANDE_001152_1.jpg</foto>
<foto>http://www.souzaveiculos.com.br/veiculos/001152/GRANDE_001152_2.jpg</foto>
<foto>http://www.souzaveiculos.com.br/veiculos/001152/GRANDE_001152_3.jpg</foto>
<foto>http://www.souzaveiculos.com.br/veiculos/001152/GRANDE_001152_4.jpg</foto>
</fotos>
<data>11/11/2013</data>
</veiculo>
<veiculo>
<idQueBarato>11314858</idQueBarato>
<cnpj_con>01968052000119</cnpj_con>
<idveiculo>1171</idveiculo>
<tipoveiculo>Carro</tipoveiculo>
<zerokm>S</zerokm>
<placa>XXX4320</placa>
<titulo>FORD FIESTA SEDAN 2013 1.6 FLEX</titulo>
<marca>Ford</marca>
<modelo>Fiesta Sedan</modelo>
<versao><![CDATA[]]></versao>
<ano_fabricacao>2013</ano_fabricacao>
<ano_modelo>2013</ano_modelo>
<portas>4</portas>
<motorizacao>1.6</motorizacao>
<combustivel>Flex</combustivel>
<cor>Prata</cor>
<cambio>Manual</cambio>
<final_placa>0</final_placa>
<quilometragem>0</quilometragem>
<descricao><![CDATA[Veículo FORD FOX 1.6 2013/2013 FLEX de cor Prata com ótimo preço. Viabilizamos financiamento em ate 60 Meses, fazemos Troca com Troco. Temos parceria com diversos bancos e financeiras. Aceitamos seu usado na troca. Veículos revisados e com garantia.<br><br>Revenda: Souza Veículos - Para entrar em contato com esta revenda ligue para (11)4783-4722 e informe o CÓDIGO DO ANÚNCIO: 00001171.<br><br>Veja mais anúncios desta revenda em <a href='http://www.querocarros.com'>www.querocarros.com</a><br><br>Anúncio publicado através do it-Car. ]]></descricao>
<preco>38990</preco>
<observacoes></observacoes>
<tipo>Novo</tipo>
<procedencia>Nacional</procedencia>
<opcionais>
<opcional>Vidros elétricos dianteiros e traseiros</opcional>
<opcional>Vidros elétricos dianteiros</opcional>
<opcional>Travas elétricas</opcional>
<opcional>Trava central</opcional>
<opcional>Para-Choque na cor do veículo</opcional>
<opcional>Maçaneta na cor do veículo</opcional>
<opcional>Limpador traseiro</opcional>
<opcional>Direção hidráulica</opcional>
<opcional>Desembaçador traseiro</opcional>
<opcional>Chave codificada (Code)</opcional>
<opcional>Câmbio manual</opcional>
<opcional>Ar-quente</opcional>
<opcional>Ar-condicionado</opcional>
<opcional>Alarme à distância</opcional>
<opcional>Alarme</opcional>
<opcional>Airbag passageiro</opcional>
<opcional>Airbag motorista</opcional>
</opcionais>
<fotos>
<foto>http://www.souzaveiculos.com.br/veiculos/001171/GRANDE_001171_1.jpg</foto>
<foto>http://www.souzaveiculos.com.br/veiculos/001171/GRANDE_001171_2.jpg</foto>
<foto>http://www.souzaveiculos.com.br/veiculos/001171/GRANDE_001171_3.jpg</foto>
<foto>http://www.souzaveiculos.com.br/veiculos/001171/GRANDE_001171_4.jpg</foto>
<foto>http://www.souzaveiculos.com.br/veiculos/001171/GRANDE_001171_5.jpg</foto>
</fotos>
<data>11/11/2013</data>
</veiculo>
<veiculo>
<idQueBarato>11314860</idQueBarato>
<cnpj_con></cnpj_con>
<idveiculo>1171</idveiculo>
<tipoveiculo>Carro</tipoveiculo>
<zerokm>S</zerokm>
<placa>XXX4320</placa>
<titulo>FORD FIESTA SEDAN 2013 1.6 FLEX</titulo>
<marca>Ford</marca>
<modelo>Fiesta Sedan</modelo>
<versao><![CDATA[]]></versao>
<ano_fabricacao>2013</ano_fabricacao>
<ano_modelo>2013</ano_modelo>
<portas>4</portas>
<motorizacao>1.6</motorizacao>
<combustivel>Flex</combustivel>
<cor>Prata</cor>
<cambio>Manual</cambio>
<final_placa>0</final_placa>
<quilometragem>0</quilometragem>
<descricao><![CDATA[Veículo FORD FIESTA SEDAN 1.6 2013/2013 FLEX de cor Prata com ótimo preço. Viabilizamos financiamento em ate 60 Meses, fazemos Troca com Troco. Temos parceria com diversos bancos e financeiras. Aceitamos seu usado na troca. Veículos revisados e com garantia.<br><br>Revenda: Souza Veículos - Para entrar em contato com esta revenda ligue para (11)4203-2689 e informe o CÓDIGO DO ANÚNCIO: 00001171.<br><br>Veja mais anúncios desta revenda em <a href='http://www.querocarros.com'>www.querocarros.com</a><br><br>Anúncio publicado através do it-Car. ]]></descricao>
<preco>38990</preco>
<observacoes></observacoes>
<tipo>Novo</tipo>
<procedencia>Nacional</procedencia>
<opcionais>
<opcional>Vidros elétricos dianteiros e traseiros</opcional>
<opcional>Vidros elétricos dianteiros</opcional>
<opcional>Travas elétricas</opcional>
<opcional>Trava central</opcional>
<opcional>Para-Choque na cor do veículo</opcional>
<opcional>Maçaneta na cor do veículo</opcional>
<opcional>Limpador traseiro</opcional>
<opcional>Direção hidráulica</opcional>
<opcional>Desembaçador traseiro</opcional>
<opcional>Chave codificada (Code)</opcional>
<opcional>Câmbio manual</opcional>
<opcional>Ar-quente</opcional>
<opcional>Ar-condicionado</opcional>
<opcional>Alarme à distância</opcional>
<opcional>Alarme</opcional>
<opcional>Airbag passageiro</opcional>
<opcional>Airbag motorista</opcional>
</opcionais>
<fotos>
<foto>http://www.souzaveiculos.com.br/veiculos/001171/GRANDE_001171_1.jpg</foto>
<foto>http://www.souzaveiculos.com.br/veiculos/001171/GRANDE_001171_2.jpg</foto>
<foto>http://www.souzaveiculos.com.br/veiculos/001171/GRANDE_001171_3.jpg</foto>
<foto>http://www.souzaveiculos.com.br/veiculos/001171/GRANDE_001171_4.jpg</foto>
<foto>http://www.souzaveiculos.com.br/veiculos/001171/GRANDE_001171_5.jpg</foto>
</fotos>
<data>11/11/2013</data>
</veiculo>
<veiculo>
<idQueBarato>11314869</idQueBarato>
<cnpj_con>01968052000119</cnpj_con>
<idveiculo>1193</idveiculo>
<tipoveiculo>Carro</tipoveiculo>
<zerokm>N</zerokm>
<placa>DPG0800</placa>
<titulo>AUDI A3 2004 1.8 GASOLINA</titulo>
<marca>Audi</marca>
<modelo>A3</modelo>
<versao><![CDATA[]]></versao>
<ano_fabricacao>2004</ano_fabricacao>
<ano_modelo>2005</ano_modelo>
<portas>4</portas>
<motorizacao>1.8</motorizacao>
<combustivel>Gasolina</combustivel>
<cor>Preto</cor>
<cambio>Manual</cambio>
<final_placa>0</final_placa>
<quilometragem>84500</quilometragem>
<descricao><![CDATA[Veículo AUDI FIESTA SEDAN 1.8 2004/2005 GASOLINA de cor Preto com ótimo preço. Viabilizamos financiamento em ate 60 Meses, fazemos Troca com Troco. Temos parceria com diversos bancos e financeiras. Aceitamos seu usado na troca. Veículos revisados e com garantia.<br><br>Revenda: Souza Veículos - Para entrar em contato com esta revenda ligue para (11)4783-4722 e informe o CÓDIGO DO ANÚNCIO: 00001193.<br><br>Veja mais anúncios desta revenda em <a href='http://www.querocarros.com'>www.querocarros.com</a><br><br>Anúncio publicado através do it-Car. ]]></descricao>
<preco>27900</preco>
<observacoes></observacoes>
<tipo>Usado</tipo>
<procedencia>Nacional</procedencia>
<opcionais>
<opcional>Vidros elétricos dianteiros e traseiros</opcional>
<opcional>Vidros elétricos dianteiros</opcional>
<opcional>Travas elétricas</opcional>
<opcional>Trava central</opcional>
<opcional>Limpador traseiro</opcional>
<opcional>Insul Film</opcional>
<opcional>Direção hidráulica</opcional>
<opcional>Desembaçador traseiro</opcional>
<opcional>Bancos de couro</opcional>
<opcional>Ar-quente</opcional>
<opcional>Ar-condicionado</opcional>
<opcional>Alarme à distância</opcional>
<opcional>Alarme</opcional>
<opcional>Airbag passageiro</opcional>
<opcional>Airbag motorista</opcional>
<opcional>Air bag Lateral Traseiro</opcional>
<opcional>Air bag Lateral Dianteiro</opcional>
</opcionais>
<fotos>
<foto>http://www.querocarros.com/imagens/sem_foto_grande.jpg</foto>
</fotos>
<data>11/11/2013</data>
</veiculo>
<veiculo>
<idQueBarato>11314871</idQueBarato>
<cnpj_con></cnpj_con>
<idveiculo>1193</idveiculo>
<tipoveiculo>Carro</tipoveiculo>
<zerokm>N</zerokm>
<placa>DPG0800</placa>
<titulo>AUDI A3 2004 1.8 GASOLINA</titulo>
<marca>Audi</marca>
<modelo>A3</modelo>
<versao><![CDATA[]]></versao>
<ano_fabricacao>2004</ano_fabricacao>
<ano_modelo>2005</ano_modelo>
<portas>4</portas>
<motorizacao>1.8</motorizacao>
<combustivel>Gasolina</combustivel>
<cor>Preto</cor>
<cambio>Manual</cambio>
<final_placa>0</final_placa>
<quilometragem>84500</quilometragem>
<descricao><![CDATA[Veículo AUDI A3 1.8 2004/2005 GASOLINA de cor Preto com ótimo preço. Viabilizamos financiamento em ate 60 Meses, fazemos Troca com Troco. Temos parceria com diversos bancos e financeiras. Aceitamos seu usado na troca. Veículos revisados e com garantia.<br><br>Revenda: Souza Veículos - Para entrar em contato com esta revenda ligue para (11)4203-2689 e informe o CÓDIGO DO ANÚNCIO: 00001193.<br><br>Veja mais anúncios desta revenda em <a href='http://www.querocarros.com'>www.querocarros.com</a><br><br>Anúncio publicado através do it-Car. ]]></descricao>
<preco>27900</preco>
<observacoes></observacoes>
<tipo>Usado</tipo>
<procedencia>Nacional</procedencia>
<opcionais>
<opcional>Vidros elétricos dianteiros e traseiros</opcional>
<opcional>Vidros elétricos dianteiros</opcional>
<opcional>Travas elétricas</opcional>
<opcional>Trava central</opcional>
<opcional>Limpador traseiro</opcional>
<opcional>Insul Film</opcional>
<opcional>Direção hidráulica</opcional>
<opcional>Desembaçador traseiro</opcional>
<opcional>Bancos de couro</opcional>
<opcional>Ar-quente</opcional>
<opcional>Ar-condicionado</opcional>
<opcional>Alarme à distância</opcional>
<opcional>Alarme</opcional>
<opcional>Airbag passageiro</opcional>
<opcional>Airbag motorista</opcional>
<opcional>Air bag Lateral Traseiro</opcional>
<opcional>Air bag Lateral Dianteiro</opcional>
</opcionais>
<fotos>
<foto>http://www.querocarros.com/imagens/sem_foto_grande.jpg</foto>
</fotos>
<data>11/11/2013</data>
</veiculo>
<veiculo>
<idQueBarato>11314877</idQueBarato>
<cnpj_con>01968052000119</cnpj_con>
<idveiculo>1202</idveiculo>
<tipoveiculo>Carro</tipoveiculo>
<zerokm>N</zerokm>
<placa>EBR4841</placa>
<titulo>HONDA CIVIC 2008 1.8 FLEX</titulo>
<marca>Honda</marca>
<modelo>Civic</modelo>
<versao><![CDATA[Civic Sedan LXS 1.8/1.8 Flex 16V Mec. 4p]]></versao>
<ano_fabricacao>2008</ano_fabricacao>
<ano_modelo>2008</ano_modelo>
<portas>4</portas>
<motorizacao>1.8</motorizacao>
<combustivel>Flex</combustivel>
<cor>Preto</cor>
<cambio>Manual</cambio>
<final_placa>1</final_placa>
<quilometragem>39653</quilometragem>
<descricao><![CDATA[Veículo HONDA A3 1.8 2008/2008 FLEX de cor Preto com ótimo preço. Viabilizamos financiamento em ate 60 Meses, fazemos Troca com Troco. Temos parceria com diversos bancos e financeiras. Aceitamos seu usado na troca. Veículos revisados e com garantia.<br><br>Revenda: Souza Veículos - Para entrar em contato com esta revenda ligue para (11)4783-4722 e informe o CÓDIGO DO ANÚNCIO: 00001202.<br><br>Veja mais anúncios desta revenda em <a href='http://www.querocarros.com'>www.querocarros.com</a><br><br>Anúncio publicado através do it-Car. ]]></descricao>
<preco>36900</preco>
<observacoes></observacoes>
<tipo>Usado</tipo>
<procedencia>Nacional</procedencia>
<opcionais>
<opcional>Vidros elétricos dianteiros e traseiros</opcional>
<opcional>Travas elétricas</opcional>
<opcional>Trava central</opcional>
<opcional>Rádio FM/AM</opcional>
<opcional>Insul Film</opcional>
<opcional>Direção hidráulica</opcional>
<opcional>CD player</opcional>
<opcional>Câmbio manual</opcional>
<opcional>Bancos de couro</opcional>
<opcional>Ar-quente</opcional>
<opcional>Ar-condicionado</opcional>
<opcional>Alarme à distância</opcional>
<opcional>Alarme</opcional>
</opcionais>
<fotos>
<foto>http://www.souzaveiculos.com.br/veiculos/001202/GRANDE_001202_1.jpg</foto>
<foto>http://www.souzaveiculos.com.br/veiculos/001202/GRANDE_001202_2.jpg</foto>
<foto>http://www.souzaveiculos.com.br/veiculos/001202/GRANDE_001202_3.jpg</foto>
<foto>http://www.souzaveiculos.com.br/veiculos/001202/GRANDE_001202_4.jpg</foto>
</fotos>
<data>11/11/2013</data>
</veiculo>
<veiculo>
<idQueBarato>11314878</idQueBarato>
<cnpj_con></cnpj_con>
<idveiculo>1202</idveiculo>
<tipoveiculo>Carro</tipoveiculo>
<zerokm>N</zerokm>
<placa>EBR4841</placa>
<titulo>HONDA CIVIC 2008 1.8 FLEX</titulo>
<marca>Honda</marca>
<modelo>Civic</modelo>
<versao><![CDATA[Civic Sedan LXS 1.8/1.8 Flex 16V Mec. 4p]]></versao>
<ano_fabricacao>2008</ano_fabricacao>
<ano_modelo>2008</ano_modelo>
<portas>4</portas>
<motorizacao>1.8</motorizacao>
<combustivel>Flex</combustivel>
<cor>Preto</cor>
<cambio>Manual</cambio>
<final_placa>1</final_placa>
<quilometragem>39653</quilometragem>
<descricao><![CDATA[Veículo HONDA CIVIC 1.8 2008/2008 FLEX de cor Preto com ótimo preço. Viabilizamos financiamento em ate 60 Meses, fazemos Troca com Troco. Temos parceria com diversos bancos e financeiras. Aceitamos seu usado na troca. Veículos revisados e com garantia.<br><br>Revenda: Souza Veículos - Para entrar em contato com esta revenda ligue para (11)4203-2689 e informe o CÓDIGO DO ANÚNCIO: 00001202.<br><br>Veja mais anúncios desta revenda em <a href='http://www.querocarros.com'>www.querocarros.com</a><br><br>Anúncio publicado através do it-Car. ]]></descricao>
<preco>36900</preco>
<observacoes></observacoes>
<tipo>Usado</tipo>
<procedencia>Nacional</procedencia>
<opcionais>
<opcional>Vidros elétricos dianteiros e traseiros</opcional>
<opcional>Travas elétricas</opcional>
<opcional>Trava central</opcional>
<opcional>Rádio FM/AM</opcional>
<opcional>Insul Film</opcional>
<opcional>Direção hidráulica</opcional>
<opcional>CD player</opcional>
<opcional>Câmbio manual</opcional>
<opcional>Bancos de couro</opcional>
<opcional>Ar-quente</opcional>
<opcional>Ar-condicionado</opcional>
<opcional>Alarme à distância</opcional>
<opcional>Alarme</opcional>
</opcionais>
<fotos>
<foto>http://www.souzaveiculos.com.br/veiculos/001202/GRANDE_001202_1.jpg</foto>
<foto>http://www.souzaveiculos.com.br/veiculos/001202/GRANDE_001202_2.jpg</foto>
<foto>http://www.souzaveiculos.com.br/veiculos/001202/GRANDE_001202_3.jpg</foto>
<foto>http://www.souzaveiculos.com.br/veiculos/001202/GRANDE_001202_4.jpg</foto>
</fotos>
<data>11/11/2013</data>
</veiculo>
<veiculo>
<idQueBarato>11314881</idQueBarato>
<cnpj_con>01968052000119</cnpj_con>
<idveiculo>1210</idveiculo>
<tipoveiculo>Carro</tipoveiculo>
<zerokm>N</zerokm>
<placa>BOJ8321</placa>
<titulo>CHEVROLET KADETT 1994 1.8 GASOLINA</titulo>
<marca>Chevrolet</marca>
<modelo>Kadett</modelo>
<versao><![CDATA[Kadett GL/SL/Lite/Turim 1.8]]></versao>
<ano_fabricacao>1994</ano_fabricacao>
<ano_modelo>1994</ano_modelo>
<portas>2</portas>
<motorizacao>1.8</motorizacao>
<combustivel>Gasolina</combustivel>
<cor>Preto</cor>
<cambio>Manual</cambio>
<final_placa>1</final_placa>
<quilometragem>1</quilometragem>
<descricao><![CDATA[Veículo CHEVROLET CIVIC 1.8 1994/1994 GASOLINA de cor Preto com ótimo preço. Viabilizamos financiamento em ate 60 Meses, fazemos Troca com Troco. Temos parceria com diversos bancos e financeiras. Aceitamos seu usado na troca. Veículos revisados e com garantia.<br><br>Revenda: Souza Veículos - Para entrar em contato com esta revenda ligue para (11)4783-4722 e informe o CÓDIGO DO ANÚNCIO: 00001210.<br><br>Veja mais anúncios desta revenda em <a href='http://www.querocarros.com'>www.querocarros.com</a><br><br>Anúncio publicado através do it-Car. ]]></descricao>
<preco>8500</preco>
<observacoes></observacoes>
<tipo>Usado</tipo>
<procedencia>Nacional</procedencia>
<opcionais>
<opcional>Vidros elétricos dianteiros</opcional>
<opcional>Limpador traseiro</opcional>
<opcional>Insul Film</opcional>
<opcional>Desembaçador traseiro</opcional>
<opcional>Alarme</opcional>
</opcionais>
<fotos>
<foto>http://www.querocarros.com/imagens/sem_foto_grande.jpg</foto>
</fotos>
<data>11/11/2013</data>
</veiculo>
<veiculo>
<idQueBarato>11314883</idQueBarato>
<cnpj_con></cnpj_con>
<idveiculo>1210</idveiculo>
<tipoveiculo>Carro</tipoveiculo>
<zerokm>N</zerokm>
<placa>BOJ8321</placa>
<titulo>CHEVROLET KADETT 1994 1.8 GASOLINA</titulo>
<marca>Chevrolet</marca>
<modelo>Kadett</modelo>
<versao><![CDATA[Kadett GL/SL/Lite/Turim 1.8]]></versao>
<ano_fabricacao>1994</ano_fabricacao>
<ano_modelo>1994</ano_modelo>
<portas>2</portas>
<motorizacao>1.8</motorizacao>
<combustivel>Gasolina</combustivel>
<cor>Preto</cor>
<cambio>Manual</cambio>
<final_placa>1</final_placa>
<quilometragem>1</quilometragem>
<descricao><![CDATA[Veículo CHEVROLET KADETT 1.8 1994/1994 GASOLINA de cor Preto com ótimo preço. Viabilizamos financiamento em ate 60 Meses, fazemos Troca com Troco. Temos parceria com diversos bancos e financeiras. Aceitamos seu usado na troca. Veículos revisados e com garantia.<br><br>Revenda: Souza Veículos - Para entrar em contato com esta revenda ligue para (11)4203-2689 e informe o CÓDIGO DO ANÚNCIO: 00001210.<br><br>Veja mais anúncios desta revenda em <a href='http://www.querocarros.com'>www.querocarros.com</a><br><br>Anúncio publicado através do it-Car. ]]></descricao>
<preco>8500</preco>
<observacoes></observacoes>
<tipo>Usado</tipo>
<procedencia>Nacional</procedencia>
<opcionais>
<opcional>Vidros elétricos dianteiros</opcional>
<opcional>Limpador traseiro</opcional>
<opcional>Insul Film</opcional>
<opcional>Desembaçador traseiro</opcional>
<opcional>Alarme</opcional>
</opcionais>
<fotos>
<foto>http://www.querocarros.com/imagens/sem_foto_grande.jpg</foto>
</fotos>
<data>11/11/2013</data>
</veiculo>
<veiculo>
<idQueBarato>11314884</idQueBarato>
<cnpj_con>01968052000119</cnpj_con>
<idveiculo>1209</idveiculo>
<tipoveiculo>Carro</tipoveiculo>
<zerokm>N</zerokm>
<placa>EDQ4746</placa>
<titulo>CHEVROLET PRISMA 2008 1.4 FLEX</titulo>
<marca>Chevrolet</marca>
<modelo>Prisma</modelo>
<versao><![CDATA[PRISMA Sed. Joy 1.4 8V ECONOFLEX 4p]]></versao>
<ano_fabricacao>2008</ano_fabricacao>
<ano_modelo>2009</ano_modelo>
<portas>4</portas>
<motorizacao>1.4</motorizacao>
<combustivel>Flex</combustivel>
<cor>Preto</cor>
<cambio>Manual</cambio>
<final_placa>6</final_placa>
<quilometragem>155000</quilometragem>
<descricao><![CDATA[Veículo CHEVROLET KADETT 1.4 2008/2009 FLEX de cor Preto com ótimo preço. Viabilizamos financiamento em ate 60 Meses, fazemos Troca com Troco. Temos parceria com diversos bancos e financeiras. Aceitamos seu usado na troca. Veículos revisados e com garantia.<br><br>Revenda: Souza Veículos - Para entrar em contato com esta revenda ligue para (11)4783-4722 e informe o CÓDIGO DO ANÚNCIO: 00001209.<br><br>Veja mais anúncios desta revenda em <a href='http://www.querocarros.com'>www.querocarros.com</a><br><br>Anúncio publicado através do it-Car. ]]></descricao>
<preco>19900</preco>
<observacoes></observacoes>
<tipo>Usado</tipo>
<procedencia>Nacional</procedencia>
<opcionais>
<opcional>Ar-condicionado</opcional>
</opcionais>
<fotos>
<foto>http://www.souzaveiculos.com.br/veiculos/001209/GRANDE_001209_1.jpg</foto>
<foto>http://www.souzaveiculos.com.br/veiculos/001209/GRANDE_001209_2.jpg</foto>
<foto>http://www.souzaveiculos.com.br/veiculos/001209/GRANDE_001209_3.jpg</foto>
<foto>http://www.souzaveiculos.com.br/veiculos/001209/GRANDE_001209_4.jpg</foto>
<foto>http://www.souzaveiculos.com.br/veiculos/001209/GRANDE_001209_5.jpg</foto>
</fotos>
<data>11/11/2013</data>
</veiculo>
<veiculo>
<idQueBarato>11314886</idQueBarato>
<cnpj_con></cnpj_con>
<idveiculo>1209</idveiculo>
<tipoveiculo>Carro</tipoveiculo>
<zerokm>N</zerokm>
<placa>EDQ4746</placa>
<titulo>CHEVROLET PRISMA 2008 1.4 FLEX</titulo>
<marca>Chevrolet</marca>
<modelo>Prisma</modelo>
<versao><![CDATA[PRISMA Sed. Joy 1.4 8V ECONOFLEX 4p]]></versao>
<ano_fabricacao>2008</ano_fabricacao>
<ano_modelo>2009</ano_modelo>
<portas>4</portas>
<motorizacao>1.4</motorizacao>
<combustivel>Flex</combustivel>
<cor>Preto</cor>
<cambio>Manual</cambio>
<final_placa>6</final_placa>
<quilometragem>155000</quilometragem>
<descricao><![CDATA[Veículo CHEVROLET PRISMA 1.4 2008/2009 FLEX de cor Preto com ótimo preço. Viabilizamos financiamento em ate 60 Meses, fazemos Troca com Troco. Temos parceria com diversos bancos e financeiras. Aceitamos seu usado na troca. Veículos revisados e com garantia.<br><br>Revenda: Souza Veículos - Para entrar em contato com esta revenda ligue para (11)4203-2689 e informe o CÓDIGO DO ANÚNCIO: 00001209.<br><br>Veja mais anúncios desta revenda em <a href='http://www.querocarros.com'>www.querocarros.com</a><br><br>Anúncio publicado através do it-Car. ]]></descricao>
<preco>19900</preco>
<observacoes></observacoes>
<tipo>Usado</tipo>
<procedencia>Nacional</procedencia>
<opcionais>
<opcional>Ar-condicionado</opcional>
</opcionais>
<fotos>
<foto>http://www.souzaveiculos.com.br/veiculos/001209/GRANDE_001209_1.jpg</foto>
<foto>http://www.souzaveiculos.com.br/veiculos/001209/GRANDE_001209_2.jpg</foto>
<foto>http://www.souzaveiculos.com.br/veiculos/001209/GRANDE_001209_3.jpg</foto>
<foto>http://www.souzaveiculos.com.br/veiculos/001209/GRANDE_001209_4.jpg</foto>
<foto>http://www.souzaveiculos.com.br/veiculos/001209/GRANDE_001209_5.jpg</foto>
</fotos>
<data>11/11/2013</data>
</veiculo>
<veiculo>
<idQueBarato>11314889</idQueBarato>
<cnpj_con>01968052000119</cnpj_con>
<idveiculo>1217</idveiculo>
<tipoveiculo>Carro</tipoveiculo>
<zerokm>N</zerokm>
<placa>DNI0249</placa>
<titulo>CHEVROLET ZAFIRA 2005 2.0 FLEX</titulo>
<marca>Chevrolet</marca>
<modelo>Zafira</modelo>
<versao><![CDATA[Zafira Eleg.2.0 MPFI FlexPower 8V 5p Aut]]></versao>
<ano_fabricacao>2005</ano_fabricacao>
<ano_modelo>2006</ano_modelo>
<portas>4</portas>
<motorizacao>2.0</motorizacao>
<combustivel>Flex</combustivel>
<cor>Prata</cor>
<cambio>Automática</cambio>
<final_placa>9</final_placa>
<quilometragem>105874</quilometragem>
<descricao><![CDATA[Veículo CHEVROLET PRISMA 2.0 2005/2006 FLEX de cor Prata com ótimo preço. Viabilizamos financiamento em ate 60 Meses, fazemos Troca com Troco. Temos parceria com diversos bancos e financeiras. Aceitamos seu usado na troca. Veículos revisados e com garantia.<br><br>Revenda: Souza Veículos - Para entrar em contato com esta revenda ligue para (11)4783-4722 e informe o CÓDIGO DO ANÚNCIO: 00001217.<br><br>Veja mais anúncios desta revenda em <a href='http://www.querocarros.com'>www.querocarros.com</a><br><br>Anúncio publicado através do it-Car. ]]></descricao>
<preco>32900</preco>
<observacoes></observacoes>
<tipo>Usado</tipo>
<procedencia>Nacional</procedencia>
<opcionais>
</opcionais>
<fotos>
<foto>http://www.souzaveiculos.com.br/veiculos/001217/GRANDE_001217_1.jpg</foto>
<foto>http://www.souzaveiculos.com.br/veiculos/001217/GRANDE_001217_2.jpg</foto>
<foto>http://www.souzaveiculos.com.br/veiculos/001217/GRANDE_001217_3.jpg</foto>
<foto>http://www.souzaveiculos.com.br/veiculos/001217/GRANDE_001217_4.jpg</foto>
<foto>http://www.souzaveiculos.com.br/veiculos/001217/GRANDE_001217_5.jpg</foto>
<foto>http://www.souzaveiculos.com.br/veiculos/001217/GRANDE_001217_6.jpg</foto>
<foto>http://www.souzaveiculos.com.br/veiculos/001217/GRANDE_001217_7.jpg</foto>
</fotos>
<data>11/11/2013</data>
</veiculo>
<veiculo>
<idQueBarato>11314890</idQueBarato>
<cnpj_con></cnpj_con>
<idveiculo>1217</idveiculo>
<tipoveiculo>Carro</tipoveiculo>
<zerokm>N</zerokm>
<placa>DNI0249</placa>
<titulo>CHEVROLET ZAFIRA 2005 2.0 FLEX</titulo>
<marca>Chevrolet</marca>
<modelo>Zafira</modelo>
<versao><![CDATA[Zafira Eleg.2.0 MPFI FlexPower 8V 5p Aut]]></versao>
<ano_fabricacao>2005</ano_fabricacao>
<ano_modelo>2006</ano_modelo>
<portas>4</portas>
<motorizacao>2.0</motorizacao>
<combustivel>Flex</combustivel>
<cor>Prata</cor>
<cambio>Automática</cambio>
<final_placa>9</final_placa>
<quilometragem>105874</quilometragem>
<descricao><![CDATA[Veículo CHEVROLET ZAFIRA 2.0 2005/2006 FLEX de cor Prata com ótimo preço. Viabilizamos financiamento em ate 60 Meses, fazemos Troca com Troco. Temos parceria com diversos bancos e financeiras. Aceitamos seu usado na troca. Veículos revisados e com garantia.<br><br>Revenda: Souza Veículos - Para entrar em contato com esta revenda ligue para (11)4203-2689 e informe o CÓDIGO DO ANÚNCIO: 00001217.<br><br>Veja mais anúncios desta revenda em <a href='http://www.querocarros.com'>www.querocarros.com</a><br><br>Anúncio publicado através do it-Car. ]]></descricao>
<preco>32900</preco>
<observacoes></observacoes>
<tipo>Usado</tipo>
<procedencia>Nacional</procedencia>
<opcionais>
</opcionais>
<fotos>
<foto>http://www.souzaveiculos.com.br/veiculos/001217/GRANDE_001217_1.jpg</foto>
<foto>http://www.souzaveiculos.com.br/veiculos/001217/GRANDE_001217_2.jpg</foto>
<foto>http://www.souzaveiculos.com.br/veiculos/001217/GRANDE_001217_3.jpg</foto>
<foto>http://www.souzaveiculos.com.br/veiculos/001217/GRANDE_001217_4.jpg</foto>
<foto>http://www.souzaveiculos.com.br/veiculos/001217/GRANDE_001217_5.jpg</foto>
<foto>http://www.souzaveiculos.com.br/veiculos/001217/GRANDE_001217_6.jpg</foto>
<foto>http://www.souzaveiculos.com.br/veiculos/001217/GRANDE_001217_7.jpg</foto>
</fotos>
<data>11/11/2013</data>
</veiculo>
<veiculo>
<idQueBarato>11314896</idQueBarato>
<cnpj_con>01968052000119</cnpj_con>
<idveiculo>1212</idveiculo>
<tipoveiculo>Carro</tipoveiculo>
<zerokm>N</zerokm>
<placa>DCX9529</placa>
<titulo>CHEVROLET CORSA 2001 1.0 GASOLINA</titulo>
<marca>Chevrolet</marca>
<modelo>Corsa</modelo>
<versao><![CDATA[Corsa Sed.Wind 1.0/Millenium/Classic VHC]]></versao>
<ano_fabricacao>2001</ano_fabricacao>
<ano_modelo>2002</ano_modelo>
<portas>4</portas>
<motorizacao>1.0</motorizacao>
<combustivel>Gasolina</combustivel>
<cor>Azul</cor>
<cambio>Manual</cambio>
<final_placa>9</final_placa>
<quilometragem>100065</quilometragem>
<descricao><![CDATA[Veículo CHEVROLET ZAFIRA 1.0 2001/2002 GASOLINA de cor Azul com ótimo preço. Viabilizamos financiamento em ate 60 Meses, fazemos Troca com Troco. Temos parceria com diversos bancos e financeiras. Aceitamos seu usado na troca. Veículos revisados e com garantia.<br><br>Revenda: Souza Veículos - Para entrar em contato com esta revenda ligue para (11)4783-4722 e informe o CÓDIGO DO ANÚNCIO: 00001212.<br><br>Veja mais anúncios desta revenda em <a href='http://www.querocarros.com'>www.querocarros.com</a><br><br>Anúncio publicado através do it-Car. ]]></descricao>
<preco>13900</preco>
<observacoes></observacoes>
<tipo>Usado</tipo>
<procedencia>Nacional</procedencia>
<opcionais>
<opcional>Vidros elétricos dianteiros</opcional>
<opcional>Travas elétricas</opcional>
<opcional>Insul Film</opcional>
</opcionais>
<fotos>
<foto>http://www.souzaveiculos.com.br/veiculos/001212/GRANDE_001212_1.jpg</foto>
<foto>http://www.souzaveiculos.com.br/veiculos/001212/GRANDE_001212_2.jpg</foto>
<foto>http://www.souzaveiculos.com.br/veiculos/001212/GRANDE_001212_3.jpg</foto>
<foto>http://www.souzaveiculos.com.br/veiculos/001212/GRANDE_001212_4.jpg</foto>
<foto>http://www.souzaveiculos.com.br/veiculos/001212/GRANDE_001212_5.jpg</foto>
</fotos>
<data>11/11/2013</data>
</veiculo>
<veiculo>
<idQueBarato>11314898</idQueBarato>
<cnpj_con></cnpj_con>
<idveiculo>1212</idveiculo>
<tipoveiculo>Carro</tipoveiculo>
<zerokm>N</zerokm>
<placa>DCX9529</placa>
<titulo>CHEVROLET CORSA 2001 1.0 GASOLINA</titulo>
<marca>Chevrolet</marca>
<modelo>Corsa</modelo>
<versao><![CDATA[Corsa Sed.Wind 1.0/Millenium/Classic VHC]]></versao>
<ano_fabricacao>2001</ano_fabricacao>
<ano_modelo>2002</ano_modelo>
<portas>4</portas>
<motorizacao>1.0</motorizacao>
<combustivel>Gasolina</combustivel>
<cor>Azul</cor>
<cambio>Manual</cambio>
<final_placa>9</final_placa>
<quilometragem>100065</quilometragem>
<descricao><![CDATA[Veículo CHEVROLET CORSA 1.0 2001/2002 GASOLINA de cor Azul com ótimo preço. Viabilizamos financiamento em ate 60 Meses, fazemos Troca com Troco. Temos parceria com diversos bancos e financeiras. Aceitamos seu usado na troca. Veículos revisados e com garantia.<br><br>Revenda: Souza Veículos - Para entrar em contato com esta revenda ligue para (11)4203-2689 e informe o CÓDIGO DO ANÚNCIO: 00001212.<br><br>Veja mais anúncios desta revenda em <a href='http://www.querocarros.com'>www.querocarros.com</a><br><br>Anúncio publicado através do it-Car. ]]></descricao>
<preco>13900</preco>
<observacoes></observacoes>
<tipo>Usado</tipo>
<procedencia>Nacional</procedencia>
<opcionais>
<opcional>Vidros elétricos dianteiros</opcional>
<opcional>Travas elétricas</opcional>
<opcional>Insul Film</opcional>
</opcionais>
<fotos>
<foto>http://www.souzaveiculos.com.br/veiculos/001212/GRANDE_001212_1.jpg</foto>
<foto>http://www.souzaveiculos.com.br/veiculos/001212/GRANDE_001212_2.jpg</foto>
<foto>http://www.souzaveiculos.com.br/veiculos/001212/GRANDE_001212_3.jpg</foto>
<foto>http://www.souzaveiculos.com.br/veiculos/001212/GRANDE_001212_4.jpg</foto>
<foto>http://www.souzaveiculos.com.br/veiculos/001212/GRANDE_001212_5.jpg</foto>
</fotos>
<data>11/11/2013</data>
</veiculo>
<veiculo>
<idQueBarato>11314901</idQueBarato>
<cnpj_con>01968052000119</cnpj_con>
<idveiculo>1213</idveiculo>
<tipoveiculo>Carro</tipoveiculo>
<zerokm>N</zerokm>
<placa>EWO9645</placa>
<titulo>VOLKSWAGEN SAVEIRO 2011 1.6 FLEX</titulo>
<marca>Volkswagen</marca>
<modelo>Saveiro</modelo>
<versao><![CDATA[Saveiro CROSS 1.6 Mi Total Flex 8V CE]]></versao>
<ano_fabricacao>2011</ano_fabricacao>
<ano_modelo>2012</ano_modelo>
<portas>2</portas>
<motorizacao>1.6</motorizacao>
<combustivel>Flex</combustivel>
<cor>Preto</cor>
<cambio>Manual</cambio>
<final_placa>5</final_placa>
<quilometragem>1</quilometragem>
<descricao><![CDATA[Veículo VOLKSWAGEN CORSA 1.6 2011/2012 FLEX de cor Preto com ótimo preço. Viabilizamos financiamento em ate 60 Meses, fazemos Troca com Troco. Temos parceria com diversos bancos e financeiras. Aceitamos seu usado na troca. Veículos revisados e com garantia.<br><br>Revenda: Souza Veículos - Para entrar em contato com esta revenda ligue para (11)4783-4722 e informe o CÓDIGO DO ANÚNCIO: 00001213.<br><br>Veja mais anúncios desta revenda em <a href='http://www.querocarros.com'>www.querocarros.com</a><br><br>Anúncio publicado através do it-Car. ]]></descricao>
<preco>35900</preco>
<observacoes></observacoes>
<tipo>Usado</tipo>
<procedencia>Nacional</procedencia>
<opcionais>
</opcionais>
<fotos>
<foto>http://www.souzaveiculos.com.br/veiculos/001213/GRANDE_001213_1.jpg</foto>
<foto>http://www.souzaveiculos.com.br/veiculos/001213/GRANDE_001213_2.jpg</foto>
<foto>http://www.souzaveiculos.com.br/veiculos/001213/GRANDE_001213_3.jpg</foto>
<foto>http://www.souzaveiculos.com.br/veiculos/001213/GRANDE_001213_4.jpg</foto>
<foto>http://www.souzaveiculos.com.br/veiculos/001213/GRANDE_001213_5.jpg</foto>
</fotos>
<data>11/11/2013</data>
</veiculo>
<veiculo>
<idQueBarato>11314903</idQueBarato>
<cnpj_con></cnpj_con>
<idveiculo>1213</idveiculo>
<tipoveiculo>Carro</tipoveiculo>
<zerokm>N</zerokm>
<placa>EWO9645</placa>
<titulo>VOLKSWAGEN SAVEIRO 2011 1.6 FLEX</titulo>
<marca>Volkswagen</marca>
<modelo>Saveiro</modelo>
<versao><![CDATA[Saveiro CROSS 1.6 Mi Total Flex 8V CE]]></versao>
<ano_fabricacao>2011</ano_fabricacao>
<ano_modelo>2012</ano_modelo>
<portas>2</portas>
<motorizacao>1.6</motorizacao>
<combustivel>Flex</combustivel>
<cor>Preto</cor>
<cambio>Manual</cambio>
<final_placa>5</final_placa>
<quilometragem>1</quilometragem>
<descricao><![CDATA[Veículo VOLKSWAGEN SAVEIRO 1.6 2011/2012 FLEX de cor Preto com ótimo preço. Viabilizamos financiamento em ate 60 Meses, fazemos Troca com Troco. Temos parceria com diversos bancos e financeiras. Aceitamos seu usado na troca. Veículos revisados e com garantia.<br><br>Revenda: Souza Veículos - Para entrar em contato com esta revenda ligue para (11)4203-2689 e informe o CÓDIGO DO ANÚNCIO: 00001213.<br><br>Veja mais anúncios desta revenda em <a href='http://www.querocarros.com'>www.querocarros.com</a><br><br>Anúncio publicado através do it-Car. ]]></descricao>
<preco>35900</preco>
<observacoes></observacoes>
<tipo>Usado</tipo>
<procedencia>Nacional</procedencia>
<opcionais>
</opcionais>
<fotos>
<foto>http://www.souzaveiculos.com.br/veiculos/001213/GRANDE_001213_1.jpg</foto>
<foto>http://www.souzaveiculos.com.br/veiculos/001213/GRANDE_001213_2.jpg</foto>
<foto>http://www.souzaveiculos.com.br/veiculos/001213/GRANDE_001213_3.jpg</foto>
<foto>http://www.souzaveiculos.com.br/veiculos/001213/GRANDE_001213_4.jpg</foto>
<foto>http://www.souzaveiculos.com.br/veiculos/001213/GRANDE_001213_5.jpg</foto>
</fotos>
<data>11/11/2013</data>
</veiculo>
<veiculo>
<idQueBarato>11314906</idQueBarato>
<cnpj_con>01968052000119</cnpj_con>
<idveiculo>1216</idveiculo>
<tipoveiculo>Carro</tipoveiculo>
<zerokm>N</zerokm>
<placa>MQB1832</placa>
<titulo>CHEVROLET VECTRA 2004 2.0 GASOLINA</titulo>
<marca>Chevrolet</marca>
<modelo>Vectra</modelo>
<versao><![CDATA[Vectra GLS/Expres.2.2/ 2.0 e 2.0 CD 8V]]></versao>
<ano_fabricacao>2004</ano_fabricacao>
<ano_modelo>2004</ano_modelo>
<portas>4</portas>
<motorizacao>2.0</motorizacao>
<combustivel>Gasolina</combustivel>
<cor>Prata</cor>
<cambio>Manual</cambio>
<final_placa>2</final_placa>
<quilometragem>117809</quilometragem>
<descricao><![CDATA[Veículo CHEVROLET SAVEIRO 2.0 2004/2004 GASOLINA de cor Prata com ótimo preço. Viabilizamos financiamento em ate 60 Meses, fazemos Troca com Troco. Temos parceria com diversos bancos e financeiras. Aceitamos seu usado na troca. Veículos revisados e com garantia.<br><br>Revenda: Souza Veículos - Para entrar em contato com esta revenda ligue para (11)4783-4722 e informe o CÓDIGO DO ANÚNCIO: 00001216.<br><br>Veja mais anúncios desta revenda em <a href='http://www.querocarros.com'>www.querocarros.com</a><br><br>Anúncio publicado através do it-Car. ]]></descricao>
<preco>21900</preco>
<observacoes></observacoes>
<tipo>Usado</tipo>
<procedencia>Nacional</procedencia>
<opcionais>
<opcional>Vidros verdes</opcional>
<opcional>Vidros elétricos dianteiros e traseiros</opcional>
<opcional>Trio Elétrico</opcional>
<opcional>Travas elétricas</opcional>
<opcional>Trava central</opcional>
<opcional>Rodas de Liga Leve</opcional>
<opcional>Retrovisores Elétricos</opcional>
<opcional>Porta-copos</opcional>
<opcional>Para-Choque na cor do veículo</opcional>
<opcional>Maçaneta na cor do veículo</opcional>
<opcional>Insul Film</opcional>
<opcional>Farol de neblina</opcional>
<opcional>Espelhos elétricos</opcional>
<opcional>Entrada USB</opcional>
<opcional>Encosto de cabeça traseiro</opcional>
<opcional>Coluna de Direção Ajustável</opcional>
<opcional>Chave Cópia</opcional>
<opcional>CD player com MP3</opcional>
<opcional>CD player</opcional>
<opcional>Câmbio manual</opcional>
<opcional>Ar-quente</opcional>
<opcional>Ar-condicionado</opcional>
<opcional>Alarme</opcional>
</opcionais>
<fotos>
<foto>http://www.souzaveiculos.com.br/veiculos/001216/GRANDE_001216_1.jpg</foto>
<foto>http://www.souzaveiculos.com.br/veiculos/001216/GRANDE_001216_2.jpg</foto>
<foto>http://www.souzaveiculos.com.br/veiculos/001216/GRANDE_001216_3.jpg</foto>
<foto>http://www.souzaveiculos.com.br/veiculos/001216/GRANDE_001216_4.jpg</foto>
</fotos>
<data>11/11/2013</data>
</veiculo>
<veiculo>
<idQueBarato>11314909</idQueBarato>
<cnpj_con></cnpj_con>
<idveiculo>1216</idveiculo>
<tipoveiculo>Carro</tipoveiculo>
<zerokm>N</zerokm>
<placa>MQB1832</placa>
<titulo>CHEVROLET VECTRA 2004 2.0 GASOLINA</titulo>
<marca>Chevrolet</marca>
<modelo>Vectra</modelo>
<versao><![CDATA[Vectra GLS/Expres.2.2/ 2.0 e 2.0 CD 8V]]></versao>
<ano_fabricacao>2004</ano_fabricacao>
<ano_modelo>2004</ano_modelo>
<portas>4</portas>
<motorizacao>2.0</motorizacao>
<combustivel>Gasolina</combustivel>
<cor>Prata</cor>
<cambio>Manual</cambio>
<final_placa>2</final_placa>
<quilometragem>117809</quilometragem>
<descricao><![CDATA[Veículo CHEVROLET VECTRA 2.0 2004/2004 GASOLINA de cor Prata com ótimo preço. Viabilizamos financiamento em ate 60 Meses, fazemos Troca com Troco. Temos parceria com diversos bancos e financeiras. Aceitamos seu usado na troca. Veículos revisados e com garantia.<br><br>Revenda: Souza Veículos - Para entrar em contato com esta revenda ligue para (11)4203-2689 e informe o CÓDIGO DO ANÚNCIO: 00001216.<br><br>Veja mais anúncios desta revenda em <a href='http://www.querocarros.com'>www.querocarros.com</a><br><br>Anúncio publicado através do it-Car. ]]></descricao>
<preco>21900</preco>
<observacoes></observacoes>
<tipo>Usado</tipo>
<procedencia>Nacional</procedencia>
<opcionais>
<opcional>Vidros verdes</opcional>
<opcional>Vidros elétricos dianteiros e traseiros</opcional>
<opcional>Trio Elétrico</opcional>
<opcional>Travas elétricas</opcional>
<opcional>Trava central</opcional>
<opcional>Rodas de Liga Leve</opcional>
<opcional>Retrovisores Elétricos</opcional>
<opcional>Porta-copos</opcional>
<opcional>Para-Choque na cor do veículo</opcional>
<opcional>Maçaneta na cor do veículo</opcional>
<opcional>Insul Film</opcional>
<opcional>Farol de neblina</opcional>
<opcional>Espelhos elétricos</opcional>
<opcional>Entrada USB</opcional>
<opcional>Encosto de cabeça traseiro</opcional>
<opcional>Coluna de Direção Ajustável</opcional>
<opcional>Chave Cópia</opcional>
<opcional>CD player com MP3</opcional>
<opcional>CD player</opcional>
<opcional>Câmbio manual</opcional>
<opcional>Ar-quente</opcional>
<opcional>Ar-condicionado</opcional>
<opcional>Alarme</opcional>
</opcionais>
<fotos>
<foto>http://www.souzaveiculos.com.br/veiculos/001216/GRANDE_001216_1.jpg</foto>
<foto>http://www.souzaveiculos.com.br/veiculos/001216/GRANDE_001216_2.jpg</foto>
<foto>http://www.souzaveiculos.com.br/veiculos/001216/GRANDE_001216_3.jpg</foto>
<foto>http://www.souzaveiculos.com.br/veiculos/001216/GRANDE_001216_4.jpg</foto>
</fotos>
<data>11/11/2013</data>
</veiculo>
<veiculo>
<idQueBarato>11314916</idQueBarato>
<cnpj_con>01968052000119</cnpj_con>
<idveiculo>1219</idveiculo>
<tipoveiculo>Carro</tipoveiculo>
<zerokm>N</zerokm>
<placa>BBD0209</placa>
<titulo>CHEVROLET MONTANA 2008 1.4 FLEX</titulo>
<marca>Chevrolet</marca>
<modelo>Montana</modelo>
<versao><![CDATA[MONTANA 1.4 8V Conquest ECONOFLEX  2p]]></versao>
<ano_fabricacao>2008</ano_fabricacao>
<ano_modelo>2008</ano_modelo>
<portas>2</portas>
<motorizacao>1.4</motorizacao>
<combustivel>Flex</combustivel>
<cor>Cinza</cor>
<cambio>Manual</cambio>
<final_placa>9</final_placa>
<quilometragem>100882</quilometragem>
<descricao><![CDATA[Veículo CHEVROLET VECTRA 1.4 2008/2008 FLEX de cor Cinza com ótimo preço. Viabilizamos financiamento em ate 60 Meses, fazemos Troca com Troco. Temos parceria com diversos bancos e financeiras. Aceitamos seu usado na troca. Veículos revisados e com garantia.<br><br>Revenda: Souza Veículos - Para entrar em contato com esta revenda ligue para (11)4783-4722 e informe o CÓDIGO DO ANÚNCIO: 00001219.<br><br>Veja mais anúncios desta revenda em <a href='http://www.querocarros.com'>www.querocarros.com</a><br><br>Anúncio publicado através do it-Car. ]]></descricao>
<preco>21900</preco>
<observacoes></observacoes>
<tipo>Usado</tipo>
<procedencia>Nacional</procedencia>
<opcionais>
<opcional>Vidros elétricos dianteiros</opcional>
<opcional>Travas elétricas</opcional>
<opcional>Trava central</opcional>
<opcional>Insul Film</opcional>
<opcional>Direção hidráulica</opcional>
<opcional>Ar-condicionado</opcional>
</opcionais>
<fotos>
<foto>http://www.souzaveiculos.com.br/veiculos/001219/GRANDE_001219_1.jpg</foto>
<foto>http://www.souzaveiculos.com.br/veiculos/001219/GRANDE_001219_2.jpg</foto>
<foto>http://www.souzaveiculos.com.br/veiculos/001219/GRANDE_001219_3.jpg</foto>
<foto>http://www.souzaveiculos.com.br/veiculos/001219/GRANDE_001219_4.jpg</foto>
<foto>http://www.souzaveiculos.com.br/veiculos/001219/GRANDE_001219_5.jpg</foto>
</fotos>
<data>11/11/2013</data>
</veiculo>
<veiculo>
<idQueBarato>11314918</idQueBarato>
<cnpj_con></cnpj_con>
<idveiculo>1219</idveiculo>
<tipoveiculo>Carro</tipoveiculo>
<zerokm>N</zerokm>
<placa>BBD0209</placa>
<titulo>CHEVROLET MONTANA 2008 1.4 FLEX</titulo>
<marca>Chevrolet</marca>
<modelo>Montana</modelo>
<versao><![CDATA[MONTANA 1.4 8V Conquest ECONOFLEX  2p]]></versao>
<ano_fabricacao>2008</ano_fabricacao>
<ano_modelo>2008</ano_modelo>
<portas>2</portas>
<motorizacao>1.4</motorizacao>
<combustivel>Flex</combustivel>
<cor>Cinza</cor>
<cambio>Manual</cambio>
<final_placa>9</final_placa>
<quilometragem>100882</quilometragem>
<descricao><![CDATA[Veículo CHEVROLET MONTANA 1.4 2008/2008 FLEX de cor Cinza com ótimo preço. Viabilizamos financiamento em ate 60 Meses, fazemos Troca com Troco. Temos parceria com diversos bancos e financeiras. Aceitamos seu usado na troca. Veículos revisados e com garantia.<br><br>Revenda: Souza Veículos - Para entrar em contato com esta revenda ligue para (11)4203-2689 e informe o CÓDIGO DO ANÚNCIO: 00001219.<br><br>Veja mais anúncios desta revenda em <a href='http://www.querocarros.com'>www.querocarros.com</a><br><br>Anúncio publicado através do it-Car. ]]></descricao>
<preco>21900</preco>
<observacoes></observacoes>
<tipo>Usado</tipo>
<procedencia>Nacional</procedencia>
<opcionais>
<opcional>Vidros elétricos dianteiros</opcional>
<opcional>Travas elétricas</opcional>
<opcional>Trava central</opcional>
<opcional>Insul Film</opcional>
<opcional>Direção hidráulica</opcional>
<opcional>Ar-condicionado</opcional>
</opcionais>
<fotos>
<foto>http://www.souzaveiculos.com.br/veiculos/001219/GRANDE_001219_1.jpg</foto>
<foto>http://www.souzaveiculos.com.br/veiculos/001219/GRANDE_001219_2.jpg</foto>
<foto>http://www.souzaveiculos.com.br/veiculos/001219/GRANDE_001219_3.jpg</foto>
<foto>http://www.souzaveiculos.com.br/veiculos/001219/GRANDE_001219_4.jpg</foto>
<foto>http://www.souzaveiculos.com.br/veiculos/001219/GRANDE_001219_5.jpg</foto>
</fotos>
<data>11/11/2013</data>
</veiculo>
<veiculo>
<idQueBarato>11314921</idQueBarato>
<cnpj_con>01968052000119</cnpj_con>
<idveiculo>1220</idveiculo>
<tipoveiculo>Carro</tipoveiculo>
<zerokm>S</zerokm>
<placa>XXX0000</placa>
<titulo>FORD ECOSPORT 2013 1.6 FLEX</titulo>
<marca>Ford</marca>
<modelo>Ecosport</modelo>
<versao><![CDATA[EcoSport FREESTYLE 1.6 16V Flex 5p]]></versao>
<ano_fabricacao>2013</ano_fabricacao>
<ano_modelo>2014</ano_modelo>
<portas>4</portas>
<motorizacao>1.6</motorizacao>
<combustivel>Flex</combustivel>
<cor>Vermelho</cor>
<cambio>Manual</cambio>
<final_placa>0</final_placa>
<quilometragem>0</quilometragem>
<descricao><![CDATA[Veículo FORD MONTANA 1.6 2013/2014 FLEX de cor Vermelho com ótimo preço. Viabilizamos financiamento em ate 60 Meses, fazemos Troca com Troco. Temos parceria com diversos bancos e financeiras. Aceitamos seu usado na troca. Veículos revisados e com garantia.<br><br>Revenda: Souza Veículos - Para entrar em contato com esta revenda ligue para (11)4783-4722 e informe o CÓDIGO DO ANÚNCIO: 00001220.<br><br>Veja mais anúncios desta revenda em <a href='http://www.querocarros.com'>www.querocarros.com</a><br><br>Anúncio publicado através do it-Car. ]]></descricao>
<preco>58900</preco>
<observacoes></observacoes>
<tipo>Novo</tipo>
<procedencia>Nacional</procedencia>
<opcionais>
</opcionais>
<fotos>
<foto>http://www.souzaveiculos.com.br/veiculos/001220/GRANDE_001220_1.jpg</foto>
<foto>http://www.souzaveiculos.com.br/veiculos/001220/GRANDE_001220_2.jpg</foto>
<foto>http://www.souzaveiculos.com.br/veiculos/001220/GRANDE_001220_3.jpg</foto>
<foto>http://www.souzaveiculos.com.br/veiculos/001220/GRANDE_001220_4.jpg</foto>
<foto>http://www.souzaveiculos.com.br/veiculos/001220/GRANDE_001220_5.jpg</foto>
<foto>http://www.souzaveiculos.com.br/veiculos/001220/GRANDE_001220_6.jpg</foto>
</fotos>
<data>11/11/2013</data>
</veiculo>
<veiculo>
<idQueBarato>11314922</idQueBarato>
<cnpj_con></cnpj_con>
<idveiculo>1220</idveiculo>
<tipoveiculo>Carro</tipoveiculo>
<zerokm>S</zerokm>
<placa>XXX0000</placa>
<titulo>FORD ECOSPORT 2013 1.6 FLEX</titulo>
<marca>Ford</marca>
<modelo>Ecosport</modelo>
<versao><![CDATA[EcoSport FREESTYLE 1.6 16V Flex 5p]]></versao>
<ano_fabricacao>2013</ano_fabricacao>
<ano_modelo>2014</ano_modelo>
<portas>4</portas>
<motorizacao>1.6</motorizacao>
<combustivel>Flex</combustivel>
<cor>Vermelho</cor>
<cambio>Manual</cambio>
<final_placa>0</final_placa>
<quilometragem>0</quilometragem>
<descricao><![CDATA[Veículo FORD ECOSPORT 1.6 2013/2014 FLEX de cor Vermelho com ótimo preço. Viabilizamos financiamento em ate 60 Meses, fazemos Troca com Troco. Temos parceria com diversos bancos e financeiras. Aceitamos seu usado na troca. Veículos revisados e com garantia.<br><br>Revenda: Souza Veículos - Para entrar em contato com esta revenda ligue para (11)4203-2689 e informe o CÓDIGO DO ANÚNCIO: 00001220.<br><br>Veja mais anúncios desta revenda em <a href='http://www.querocarros.com'>www.querocarros.com</a><br><br>Anúncio publicado através do it-Car. ]]></descricao>
<preco>58900</preco>
<observacoes></observacoes>
<tipo>Novo</tipo>
<procedencia>Nacional</procedencia>
<opcionais>
</opcionais>
<fotos>
<foto>http://www.souzaveiculos.com.br/veiculos/001220/GRANDE_001220_1.jpg</foto>
<foto>http://www.souzaveiculos.com.br/veiculos/001220/GRANDE_001220_2.jpg</foto>
<foto>http://www.souzaveiculos.com.br/veiculos/001220/GRANDE_001220_3.jpg</foto>
<foto>http://www.souzaveiculos.com.br/veiculos/001220/GRANDE_001220_4.jpg</foto>
<foto>http://www.souzaveiculos.com.br/veiculos/001220/GRANDE_001220_5.jpg</foto>
<foto>http://www.souzaveiculos.com.br/veiculos/001220/GRANDE_001220_6.jpg</foto>
</fotos>
<data>11/11/2013</data>
</veiculo>
</concessionaria>
</estoque>
